{
    "type": "FeatureCollection",
    "features": [
        {
            "type": "Feature",
            "properties": {
                "label:cs": "Socha svaté Anny Samotřetí na návsi v Hošnicích",
                "P31": "http://www.wikidata.org/entity/Q179700",
                "P31^label:cs": "Socha",
                "P131^label:cs": "Strupčice",
                "P6736": "19299"
            },
            "geometry": {
                "type": "Point",
                "coordinates": [
                    13.53863,
                    50.4559
                ]
            }
        },
        {
            "type": "Feature",
            "properties": {
                "label:cs": "Sloup Nejsvětější Trojice na rozcestí v Hošnicích",
                "P31": "http://www.wikidata.org/entity/Q4817",
                "P31^label:cs": "Sloup",
                "P131^label:cs": "Strupčice",
                "P6736": "19298"
            },
            "geometry": {
                "type": "Point",
                "coordinates": [
                    13.53892,
                    50.45664
                ]
            }
        },
        {
            "type": "Feature",
            "properties": {
                "label:cs": "Kamenný kříž na východním okraji v Hošnicích",
                "P31": "http://www.wikidata.org/entity/Q2309609",
                "P31^label:cs": "Pamětní kříž",
                "P131^label:cs": "Strupčice",
                "P6736": "19297"
            },
            "geometry": {
                "type": "Point",
                "coordinates": [
                    13.54035,
                    50.45626
                ]
            }
        }
    ]
}