{
    "type": "FeatureCollection",
    "features": [
        {
            "type": "Feature",
            "properties": {
                "label:cs": "Kříž u polní cesty severně od Cítova",
                "P31": "Pamětní kříž",
                "P131^label:cs": "Cítov",
                "P6736": "22445"
            },
            "geometry": {
                "type": "Point",
                "coordinates": [
                    14.40323,
                    50.38001
                ]
            }
        },
        {
            "type": "Feature",
            "properties": {
                "label:cs": "Socha svatého Jana Nepomuckého v západní části Cítova",
                "P31": "Socha",
                "P131^label:cs": "Cítov",
                "P6736": "22441"
            },
            "geometry": {
                "type": "Point",
                "coordinates": [
                    14.38818,
                    50.37384
                ]
            }
        }
    ]
}