{
    "type": "FeatureCollection",
    "features": [
        {
            "type": "Feature",
            "properties": {
                "label:cs": "Křížový kámen v Horní Hynčině u silnice",
                "P31": "http://www.wikidata.org/entity/Q38411643",
                "P31^label:cs": "Křížový kámen",
                "P131^label:cs": "Pohledy",
                "P6736": "12317"
            },
            "geometry": {
                "type": "Point",
                "coordinates": [
                    16.53675,
                    49.66767
                ]
            }
        }
    ]
}