{"type":"FeatureCollection","features":[{"type":"Feature","properties":{"label:cs":"Kříž u křižovatky nedaleko Nového Dvora","P31":"Q2309609","P31^label:cs":"Pamětní kříž","P131^label:cs":"Mířkov","P6736":"2984"},"geometry":{"type":"Point","coordinates":[12.89891,49.57575]}},{"type":"Feature","properties":{"label:cs":"Kříž na rozcestí východně od Nového Dvora","P31":"Q2309609","P31^label:cs":"Pamětní kříž","P131^label:cs":"Mířkov","P6736":"2983"},"geometry":{"type":"Point","coordinates":[12.91195,49.57652]}},{"type":"Feature","properties":{"label:cs":"Kříž severně od Dolního Metelska","P31":"Q2309609","P31^label:cs":"Pamětní kříž","P131^label:cs":"Horšovský Týn","P6736":"2982"},"geometry":{"type":"Point","coordinates":[12.91031,49.56936]}}]}