{"type":"FeatureCollection","features":[{"type":"Feature","properties":{"label:cs":"Kaplička Panny Marie u Panského rybníka v Bochově","P31":"Kaplička","P31^label:cs":"Kaplička","P131^label:cs":"Bochov","P6736":"13812"},"geometry":{"type":"Point","coordinates":[13.03991,50.14806]}},{"type":"Feature","properties":{"label:cs":"Pomník padlým u Bochova","P31":"Pomník padlým","P31^label:cs":"Pomník padlým","P131^label:cs":"Bochov","P6736":"9442"},"geometry":{"type":"Point","coordinates":[13.04393,50.14255]}}]}