{"type":"FeatureCollection","features":[{"type":"Feature","properties":{"label:cs":"Kříž ve Skelné Huti","P31":"http://www.wikidata.org/entity/Q2309609","P31^label:cs":"Pamětní kříž","P131^label:cs":"Krsy","P6736":"3476"},"geometry":{"type":"Point","coordinates":[13.10579,49.94508]}},{"type":"Feature","properties":{"label:cs":"Menhir u Černého rybníka u Jedvanin","P31":"http://www.wikidata.org/entity/Q193475","P31^label:cs":"Menhir","P131^label:cs":"Krsy","P6736":"10279"},"geometry":{"type":"Point","coordinates":[13.10844,49.9423]}},{"type":"Feature","properties":{"label:cs":"Kříž v zahradě v Jedvaninách","P31":"http://www.wikidata.org/entity/Q2309609","P31^label:cs":"Pamětní kříž","P131^label:cs":"Krsy","P6736":"10281"},"geometry":{"type":"Point","coordinates":[13.10725,49.9434]}},{"type":"Feature","properties":{"label:cs":"Socha svatého Jana Nepomuckého v Jedvaninách","P31":"http://www.wikidata.org/entity/Q179700","P31^label:cs":"Socha","P131^label:cs":"Krsy","P6736":"10283"},"geometry":{"type":"Point","coordinates":[13.10742,49.94423]}},{"type":"Feature","properties":{"label:cs":"Kříž v Jedvaninách","P31":"http://www.wikidata.org/entity/Q2309609","P31^label:cs":"Pamětní kříž","P131^label:cs":"Nečtiny","P6736":"3474"},"geometry":{"type":"Point","coordinates":[13.10908,49.94424]}},{"type":"Feature","properties":{"label:cs":"Kříž v Jedvaninách II","P31":"http://www.wikidata.org/entity/Q2309609","P31^label:cs":"Pamětní kříž","P131^label:cs":"Nečtiny","P6736":"3475"},"geometry":{"type":"Point","coordinates":[13.10903,49.9442]}},{"type":"Feature","properties":{"label:cs":"Kříž severně od Skelné Huti nad mlýnem","P31":"http://www.wikidata.org/entity/Q2309609","P31^label:cs":"Pamětní kříž","P131^label:cs":"Nečtiny","P6736":"3477"},"geometry":{"type":"Point","coordinates":[13.10911,49.95109]}},{"type":"Feature","properties":{"label:cs":"Kříž severně od Skelné Huti u mlýna","P31":"http://www.wikidata.org/entity/Q2309609","P31^label:cs":"Pamětní kříž","P131^label:cs":"Nečtiny","P6736":"3478"},"geometry":{"type":"Point","coordinates":[13.10976,49.95102]}},{"type":"Feature","properties":{"label:cs":"Kříž v Jedvaninách III","P31":"http://www.wikidata.org/entity/Q2309609","P31^label:cs":"Pamětní kříž","P131^label:cs":"Nečtiny","P6736":"10280"},"geometry":{"type":"Point","coordinates":[13.10912,49.94428]}},{"type":"Feature","properties":{"label:cs":"Zvonička v zahradě v Jedvaninách","P31":"http://www.wikidata.org/entity/Q10861631","P31^label:cs":"Zvonička","P131^label:cs":"Nečtiny","P6736":"10282"},"geometry":{"type":"Point","coordinates":[13.1095,49.94354]}}]}