{"type":"FeatureCollection","features":[{"type":"Feature","properties":{"label:cs":"Pfeifferův kříž při silnici mezi Borkem a Žluticemi","P31":"http://www.wikidata.org/entity/Q2309609","P31^label:cs":"Pamětní kříž","P131^label:cs":"Pšov","P6736":"28231"},"geometry":{"type":"Point","coordinates":[13.15219,50.06971]}},{"type":"Feature","properties":{"label:cs":"Socha Panny Marie v Semtěši","P31":"http://www.wikidata.org/entity/Q179700","P31^label:cs":"Socha","P131^label:cs":"Pšov","P6736":"28232"},"geometry":{"type":"Point","coordinates":[13.14652,50.07159]}},{"type":"Feature","properties":{"label:cs":"Kaple v Semtěši","P31":"http://www.wikidata.org/entity/Q108325","P31^label:cs":"Kaple","P131^label:cs":"Pšov","P6736":"28233"},"geometry":{"type":"Point","coordinates":[13.1448,50.07117]}},{"type":"Feature","properties":{"label:cs":"Modlův kříž v Semtěši","P31":"http://www.wikidata.org/entity/Q2309609","P31^label:cs":"Pamětní kříž","P131^label:cs":"Pšov","P6736":"28234"},"geometry":{"type":"Point","coordinates":[13.1452,50.07047]}},{"type":"Feature","properties":{"label:cs":"Kaple svatého Antonína Poustevníka v Semtěši","P31":"http://www.wikidata.org/entity/Q14552192","P31^label:cs":"Kaplička","P131^label:cs":"Pšov","P6736":"28238"},"geometry":{"type":"Point","coordinates":[13.14187,50.07026]}},{"type":"Feature","properties":{"label:cs":"Kříž u stodoly usedlosti čp. 11 v Semtěši","P31":"http://www.wikidata.org/entity/Q2309609","P31^label:cs":"Pamětní kříž","P131^label:cs":"Pšov","P6736":"28240"},"geometry":{"type":"Point","coordinates":[13.14365,50.07077]}},{"type":"Feature","properties":{"label:cs":"Sousoší Piety při cestě na Pšov","P31":"http://www.wikidata.org/entity/Q179700","P31^label:cs":"Socha","P131^label:cs":"Pšov","P6736":"28242"},"geometry":{"type":"Point","coordinates":[13.15555,50.06897]}},{"type":"Feature","properties":{"label:cs":"Kamenný kříž jižně od Žlutic","P31":"http://www.wikidata.org/entity/Q2309609","P31^label:cs":"Pamětní kříž","P131^label:cs":"Žlutice","P6736":"28223"},"geometry":{"type":"Point","coordinates":[13.1537,50.07525]}},{"type":"Feature","properties":{"label:cs":"Schimonův kříž při odbočce na Semtěš","P31":"http://www.wikidata.org/entity/Q2309609","P31^label:cs":"Pamětní kříž","P131^label:cs":"Žlutice","P6736":"28224"},"geometry":{"type":"Point","coordinates":[13.15233,50.07254]}}]}