{"type":"FeatureCollection","features":[{"type":"Feature","properties":{"label:cs":"Kříž v Radimovicích","P31":"Q2309609","P31^label:cs":"Pamětní kříž","P131^label:cs":"Všeruby","P6736":"5507"},"geometry":{"type":"Point","coordinates":[13.20372,49.85122]}},{"type":"Feature","properties":{"label:cs":"Kaple v Radimovicích","P31":"Q108325","P31^label:cs":"Kaple","P131^label:cs":"Všeruby","P6736":"4634"},"geometry":{"type":"Point","coordinates":[13.2036,49.85138]}},{"type":"Feature","properties":{"label:cs":"Kaple severně od Hunčic","P31":"Q108325","P31^label:cs":"Kaple","P131^label:cs":"Všeruby","P6736":"3468"},"geometry":{"type":"Point","coordinates":[13.19564,49.84473]}}]}