{"type":"FeatureCollection","features":[{"type":"Feature","properties":{"label:cs":"Pomník padlým ve Zhůři","P31":"Pomník padlým","P31^label:cs":"Pomník padlým","P131^label:cs":"Chocenice","P6736":"5999"},"geometry":{"type":"Point","coordinates":[13.51865,49.5353]}},{"type":"Feature","properties":{"label:cs":"Kříž u kaple ve Zhůři","P31":"Pamětní kříž","P31^label:cs":"Pamětní kříž","P131^label:cs":"Chocenice","P6736":"5997"},"geometry":{"type":"Point","coordinates":[13.51911,49.53384]}},{"type":"Feature","properties":{"label:cs":"Kaple ve Zhůři","P31":"Kaple","P31^label:cs":"Kaple","P131^label:cs":"Chocenice","P6736":"5996"},"geometry":{"type":"Point","coordinates":[13.51899,49.53381]}}]}