{
    "type": "FeatureCollection",
    "features": [
        {
            "type": "Feature",
            "properties": {
                "label:cs": "Hrázděná zvonice u kostela v Církvicích",
                "P31": "Zvonička",
                "P31^label:cs": "Zvonička",
                "P131^label:cs": "Ústí nad Labem",
                "P6736": "15126"
            },
            "geometry": {
                "type": "Point",
                "coordinates": [
                    14.03574,
                    50.59064
                ]
            }
        },
        {
            "type": "Feature",
            "properties": {
                "label:cs": "Památník osvobození v Církvicích",
                "P31": "Památník",
                "P31^label:cs": "Památník",
                "P131^label:cs": "Ústí nad Labem",
                "P6736": "15125"
            },
            "geometry": {
                "type": "Point",
                "coordinates": [
                    14.03675,
                    50.58966
                ]
            }
        },
        {
            "type": "Feature",
            "properties": {
                "label:cs": "Kříž u silnice v Církvicích",
                "P31": "Pamětní kříž",
                "P31^label:cs": "Pamětní kříž",
                "P131^label:cs": "Ústí nad Labem",
                "P6736": "15124"
            },
            "geometry": {
                "type": "Point",
                "coordinates": [
                    14.0372,
                    50.58967
                ]
            }
        },
        {
            "type": "Feature",
            "properties": {
                "label:cs": "Pomník obětem železničního neštěstí 1962 u Církvic",
                "P31": "Pomník",
                "P31^label:cs": "Pomník",
                "P131^label:cs": "Ústí nad Labem",
                "P6736": "15123"
            },
            "geometry": {
                "type": "Point",
                "coordinates": [
                    14.03529,
                    50.58768
                ]
            }
        },
        {
            "type": "Feature",
            "properties": {
                "label:cs": "Socha svatého Jana Nepomuckého v Církvicích u kostela",
                "P31": "Socha",
                "P31^label:cs": "Socha",
                "P131^label:cs": "Ústí nad Labem",
                "P6736": "13600"
            },
            "geometry": {
                "type": "Point",
                "coordinates": [
                    14.03592,
                    50.59078
                ]
            }
        }
    ]
}