{"type":"FeatureCollection","features":[{"type":"Feature","properties":{"label:cs":"Kaple svatého Václava na hřbitově v Berouně","P31":"http://www.wikidata.org/entity/Q108325","P31^label:cs":"Kaple","P131^label:cs":"Beroun","P6736":"14965"},"geometry":{"type":"Point","coordinates":[14.06033,49.96665]}},{"type":"Feature","properties":{"label:cs":"Kaple Panny Marie Bolestné v Berouně","P31":"http://www.wikidata.org/entity/Q108325","P31^label:cs":"Kaple","P131^label:cs":"Beroun","P6736":"14972"},"geometry":{"type":"Point","coordinates":[14.0604,49.97148]}}]}