{"type":"FeatureCollection","features":[{"type":"Feature","properties":{"label:cs":"Boží muka na rozcestí cesty k hradu a silnice v Budňanech","P31":"Q3395121","P31^label:cs":"Boží muka","P131^label:cs":"Karlštejn","P6736":"14983"},"geometry":{"type":"Point","coordinates":[14.19054,49.94126]}},{"type":"Feature","properties":{"label:cs":"Socha svatého Šebestiána v Karlštejně","P31":"Q179700","P31^label:cs":"Socha","P131^label:cs":"Karlštejn","P6736":"9174"},"geometry":{"type":"Point","coordinates":[14.18692,49.93771]}},{"type":"Feature","properties":{"label:cs":"Křížek severně od hradu Karlštejn","P31":"Q2309609","P31^label:cs":"Pamětní kříž","P131^label:cs":"Karlštejn","P6736":"9173"},"geometry":{"type":"Point","coordinates":[14.18867,49.94038]}},{"type":"Feature","properties":{"label:cs":"Boží muka v areálu hradu Karlštejn","P31":"Q3395121","P31^label:cs":"Boží muka","P131^label:cs":"Karlštejn","P6736":"9171"},"geometry":{"type":"Point","coordinates":[14.18759,49.93979]}},{"type":"Feature","properties":{"label:cs":"Křížek u vstupu na hrad Karlštejn","P31":"Q2309609","P31^label:cs":"Pamětní kříž","P131^label:cs":"Karlštejn","P6736":"9170"},"geometry":{"type":"Point","coordinates":[14.18752,49.94011]}}]}