{"type":"FeatureCollection","features":[{"type":"Feature","properties":{"label:cs":"Kříž u silnice před Dolním Vysokém","P31":"http://www.wikidata.org/entity/Q2309609","P31^label:cs":"Pamětní kříž","P131^label:cs":"Úštěk","P6736":"28839"},"geometry":{"type":"Point","coordinates":[14.29459,50.60546]}},{"type":"Feature","properties":{"label:cs":"Kaple v Dolním Vysokém","P31":"http://www.wikidata.org/entity/Q108325","P31^label:cs":"Kaple","P131^label:cs":"Úštěk","P6736":"28840"},"geometry":{"type":"Point","coordinates":[14.29653,50.60415]}},{"type":"Feature","properties":{"label:cs":"Kříž u silnice z Dolního Vysokého do Habřiny","P31":"http://www.wikidata.org/entity/Q2309609","P31^label:cs":"Pamětní kříž","P131^label:cs":"Úštěk","P6736":"28841"},"geometry":{"type":"Point","coordinates":[14.30229,50.60254]}}]}