{"type":"FeatureCollection","features":[{"type":"Feature","properties":{"label:cs":"Pamětní deska francouzských zajatců 1943-45 na Domě kultury v České Kamenici","P31":"http://www.wikidata.org/entity/Q721747","P31^label:cs":"Pamětní deska","P131^label:cs":"Česká Kamenice","P6736":"41262"},"geometry":{"type":"Point","coordinates":[14.4187,50.80031]}},{"type":"Feature","properties":{"label:cs":"Socha svatého Floriána za domem 627 v České Kamenici","P31":"http://www.wikidata.org/entity/Q179700","P31^label:cs":"Socha","P131^label:cs":"Česká Kamenice","P6736":"41260"},"geometry":{"type":"Point","coordinates":[14.41999,50.80023]}},{"type":"Feature","properties":{"label:cs":"Kříž na rohu ulic Komenského a Nerudova v České Kamenici","P31":"http://www.wikidata.org/entity/Q2309609","P31^label:cs":"Pamětní kříž","P131^label:cs":"Česká Kamenice","P6736":"41258"},"geometry":{"type":"Point","coordinates":[14.41682,50.80032]}},{"type":"Feature","properties":{"label:cs":"Kašna na rohu ulic Dvořákova a Tyršova v České Kamenici","P31":"http://www.wikidata.org/entity/Q12029081","P31^label:cs":"Kašna","P131^label:cs":"Česká Kamenice","P6736":"40630"},"geometry":{"type":"Point","coordinates":[14.41451,50.79973]}},{"type":"Feature","properties":{"label:cs":"Kamenná podkova na Náměstí Míru v České Kamenici","P31":"http://www.wikidata.org/entity/Q11734477","P31^label:cs":"Památný kámen","P131^label:cs":"Česká Kamenice","P6736":"40629"},"geometry":{"type":"Point","coordinates":[14.41673,50.79971]}},{"type":"Feature","properties":{"label:cs":"Ozdobný sloup u domu 340 v České Kamenici","P31":"http://www.wikidata.org/entity/Q4817","P31^label:cs":"Sloup","P131^label:cs":"Česká Kamenice","P6736":"30088"},"geometry":{"type":"Point","coordinates":[14.42116,50.80012]}},{"type":"Feature","properties":{"label:cs":"Kříž v Havlíčkově ulici v České Kamenici","P31":"http://www.wikidata.org/entity/Q2309609","P31^label:cs":"Pamětní kříž","P131^label:cs":"Česká Kamenice","P6736":"30087"},"geometry":{"type":"Point","coordinates":[14.4226,50.79939]}},{"type":"Feature","properties":{"label:cs":"Kaplička svaté Barbory v Lipové ulici v České Kamenici","P31":"http://www.wikidata.org/entity/Q14552192","P31^label:cs":"Kaplička","P131^label:cs":"Česká Kamenice","P6736":"29651"},"geometry":{"type":"Point","coordinates":[14.42039,50.79396]}},{"type":"Feature","properties":{"label:cs":"Kříž u vstupu do areálu kaple Narození Panny Marie v České Kamenici","P31":"http://www.wikidata.org/entity/Q2309609","P31^label:cs":"Pamětní kříž","P131^label:cs":"Česká Kamenice","P6736":"29171"},"geometry":{"type":"Point","coordinates":[14.41618,50.80196]}},{"type":"Feature","properties":{"label:cs":"Kaple Narození Panny Marie v České Kamenici","P31":"http://www.wikidata.org/entity/Q108325","P31^label:cs":"Kaple","P131^label:cs":"Česká Kamenice","P6736":"29169"},"geometry":{"type":"Point","coordinates":[14.41582,50.80216]}},{"type":"Feature","properties":{"label:cs":"Kašna se sochou Panny Marie na Náměstí Míru v České Kamenici","P31":"http://www.wikidata.org/entity/Q12029081","P31^label:cs":"Kašna","P131^label:cs":"Česká Kamenice","P6736":"29161"},"geometry":{"type":"Point","coordinates":[14.41692,50.79969]}},{"type":"Feature","properties":{"label:cs":"Pomník bývalého německého střeleckého spolku nad domem seniorů ve Sládkově ulici v České Kamenici","P31":"http://www.wikidata.org/entity/Q4989906","P31^label:cs":"Pomník","P131^label:cs":"Česká Kamenice","P6736":"29160"},"geometry":{"type":"Point","coordinates":[14.42197,50.8045]}},{"type":"Feature","properties":{"label:cs":"Plastika v ulici Sládkova v České Kamenici","P31":"http://www.wikidata.org/entity/Q12045520","P31^label:cs":"Plastika","P131^label:cs":"Česká Kamenice","P6736":"29159"},"geometry":{"type":"Point","coordinates":[14.42062,50.8045]}},{"type":"Feature","properties":{"label:cs":"Kříž v ulici Máchova v České Kamenici","P31":"http://www.wikidata.org/entity/Q2309609","P31^label:cs":"Pamětní kříž","P131^label:cs":"Česká Kamenice","P6736":"29158"},"geometry":{"type":"Point","coordinates":[14.42084,50.80215]}},{"type":"Feature","properties":{"label:cs":"Kříž v ulici Zelený vrch v České Kamenici","P31":"http://www.wikidata.org/entity/Q2309609","P31^label:cs":"Pamětní kříž","P131^label:cs":"Česká Kamenice","P6736":"29157"},"geometry":{"type":"Point","coordinates":[14.42313,50.80222]}},{"type":"Feature","properties":{"label:cs":"Podstavec ulomeného kříže u domu Dukelských hrdinů 390 v České Kamenici","P31":"http://www.wikidata.org/entity/Q2309609","P31^label:cs":"Pamětní kříž","P131^label:cs":"Česká Kamenice","P6736":"29156"},"geometry":{"type":"Point","coordinates":[14.42562,50.80056]}},{"type":"Feature","properties":{"label:cs":"Pamětní kříž v Nerudově ulici v České Kamenici","P31":"http://www.wikidata.org/entity/Q2309609","P31^label:cs":"Pamětní kříž","P131^label:cs":"Česká Kamenice","P6736":"17372"},"geometry":{"type":"Point","coordinates":[14.41667,50.79968]}},{"type":"Feature","properties":{"label:cs":"Kříž nad Mariánskou kaplí v České Kamenici","P31":"http://www.wikidata.org/entity/Q2309609","P31^label:cs":"Pamětní kříž","P131^label:cs":"Česká Kamenice","P6736":"11946"},"geometry":{"type":"Point","coordinates":[14.41443,50.80268]}},{"type":"Feature","properties":{"label:cs":"Kříž v České Kamenici v Lipové ulici","P31":"http://www.wikidata.org/entity/Q2309609","P31^label:cs":"Pamětní kříž","P131^label:cs":"Česká Kamenice","P6736":"11857"},"geometry":{"type":"Point","coordinates":[14.41774,50.79771]}},{"type":"Feature","properties":{"label:cs":"Pomník padlým v České Kamenici","P31":"http://www.wikidata.org/entity/Q575759","P31^label:cs":"Pomník padlým","P131^label:cs":"Česká Kamenice","P6736":"9513"},"geometry":{"type":"Point","coordinates":[14.41595,50.80187]}}]}