{"type":"FeatureCollection","features":[{"type":"Feature","properties":{"label:cs":"Kříž u kaple ve Vítonicích","P31":"http://www.wikidata.org/entity/Q2309609","P31^label:cs":"Pamětní kříž","P131^label:cs":"Blažejovice","P6736":"29755"},"geometry":{"type":"Point","coordinates":[15.17867,49.61943]}},{"type":"Feature","properties":{"label:cs":"Kaple ve Vítonicích","P31":"http://www.wikidata.org/entity/Q108325","P31^label:cs":"Kaple","P131^label:cs":"Blažejovice","P6736":"29754"},"geometry":{"type":"Point","coordinates":[15.17855,49.61935]}}]}