{"type":"FeatureCollection","features":[{"type":"Feature","properties":{"label:cs":"Zvonice v Sumrakově","P31":"http://www.wikidata.org/entity/Q10861631","P31^label:cs":"Zvonička","P131^label:cs":"Studená","P6736":"18502"},"geometry":{"type":"Point","coordinates":[15.32059,49.17446]}},{"type":"Feature","properties":{"label:cs":"Kříž na návsi v Sumrakově","P31":"http://www.wikidata.org/entity/Q2309609","P31^label:cs":"Pamětní kříž","P131^label:cs":"Studená","P6736":"18500"},"geometry":{"type":"Point","coordinates":[15.32125,49.17427]}},{"type":"Feature","properties":{"label:cs":"Kaple Nanebevzetí Panny Marie v Sumrakově","P31":"http://www.wikidata.org/entity/Q108325","P31^label:cs":"Kaple","P131^label:cs":"Studená","P6736":"18498"},"geometry":{"type":"Point","coordinates":[15.3207,49.1743]}}]}