{"type":"FeatureCollection","features":[{"type":"Feature","properties":{"label:cs":"Socha svatého Josefa v jižní části Heřmánkovic","P31":"http://www.wikidata.org/entity/Q179700","P31^label:cs":"Socha","P131^label:cs":"Heřmánkovice","P6736":"22288"},"geometry":{"type":"Point","coordinates":[16.32419,50.61633]}},{"type":"Feature","properties":{"label:cs":"Kříž u jižního okraje Heřmánkovic","P31":"http://www.wikidata.org/entity/Q2309609","P31^label:cs":"Pamětní kříž","P131^label:cs":"Heřmánkovice","P6736":"22408"},"geometry":{"type":"Point","coordinates":[16.32371,50.61272]}}]}