{"type":"FeatureCollection","features":[{"type":"Feature","properties":{"label:cs":"Kříž v Květné v části zvané Borová krčma","P31":"Pamětní kříž","P31^label:cs":"Pamětní kříž","P131^label:cs":"Květná","P6736":"21559"},"geometry":{"type":"Point","coordinates":[16.37545,49.73414]}},{"type":"Feature","properties":{"label:cs":"Kaplička ve Vendolí západní okraj obce","P31":"Kaplička","P31^label:cs":"Kaplička","P131^label:cs":"Vendolí","P6736":"21468"},"geometry":{"type":"Point","coordinates":[16.38825,49.73512]}}]}