{"type":"FeatureCollection","features":[{"type":"Feature","properties":{"label:cs":"Pomník padlým v Lukové na hřbitově","P31":"http://www.wikidata.org/entity/Q575759","P31^label:cs":"Pomník padlým","P131^label:cs":"Luková","P6736":"27788"},"geometry":{"type":"Point","coordinates":[16.60528,49.8788]}},{"type":"Feature","properties":{"label:cs":"Pomník padlým v Lukové na rozcestí u hřiště","P31":"http://www.wikidata.org/entity/Q575759","P31^label:cs":"Pomník padlým","P131^label:cs":"Luková","P6736":"27787"},"geometry":{"type":"Point","coordinates":[16.6059,49.87672]}},{"type":"Feature","properties":{"label:cs":"Kříž v Lukové u kostela","P31":"http://www.wikidata.org/entity/Q2309609","P31^label:cs":"Pamětní kříž","P131^label:cs":"Luková","P6736":"12878"},"geometry":{"type":"Point","coordinates":[16.60543,49.87848]}},{"type":"Feature","properties":{"label:cs":"Sousoší Nejsvětější Trojice v Lukové","P31":"http://www.wikidata.org/entity/Q179700","P31^label:cs":"Socha","P131^label:cs":"Luková","P6736":"12722"},"geometry":{"type":"Point","coordinates":[16.61127,49.87552]}}]}