{"type":"FeatureCollection","features":[{"type":"Feature","properties":{"label:cs":"Pomník Antonína Kuchaříka v Rájci na okraji lesa","P31":"Pomník","P31^label:cs":"Pomník","P131^label:cs":"Rájec","P6736":"20892"},"geometry":{"type":"Point","coordinates":[16.88023,49.84829]}},{"type":"Feature","properties":{"label:cs":"Kříž západně od Zvole v lesíku","P31":"Pamětní kříž","P31^label:cs":"Pamětní kříž","P131^label:cs":"Zvole","P6736":"12826"},"geometry":{"type":"Point","coordinates":[16.89578,49.84502]}}]}