{
    "type": "FeatureCollection",
    "features": [
        {
            "type": "Feature",
            "properties": {
                "label:cs": "Pamětní deska v Zábřehu na budově městské knihovny",
                "P31": "Pamětní deska",
                "P31^label:cs": "Pamětní deska",
                "P131^label:cs": "Zábřeh",
                "P6736": "24016"
            },
            "geometry": {
                "type": "Point",
                "coordinates": [
                    16.87733,
                    49.88141
                ]
            }
        },
        {
            "type": "Feature",
            "properties": {
                "label:cs": "Pomník padlým v Zábřehu na Postřelmovské ulici",
                "P31": "Pomník padlým",
                "P31^label:cs": "Pomník padlým",
                "P131^label:cs": "Zábřeh",
                "P6736": "23827"
            },
            "geometry": {
                "type": "Point",
                "coordinates": [
                    16.88144,
                    49.88329
                ]
            }
        },
        {
            "type": "Feature",
            "properties": {
                "label:cs": "Dřevěný kříž v Zábřehu na ulici Postřelmovská",
                "P31": "Pamětní kříž",
                "P31^label:cs": "Pamětní kříž",
                "P131^label:cs": "Zábřeh",
                "P6736": "17014"
            },
            "geometry": {
                "type": "Point",
                "coordinates": [
                    16.89062,
                    49.88617
                ]
            }
        },
        {
            "type": "Feature",
            "properties": {
                "label:cs": "Kříž v Zábřehu na severním okraji města",
                "P31": "Pamětní kříž",
                "P31^label:cs": "Pamětní kříž",
                "P131^label:cs": "Zábřeh",
                "P6736": "14866"
            },
            "geometry": {
                "type": "Point",
                "coordinates": [
                    16.88069,
                    49.89235
                ]
            }
        },
        {
            "type": "Feature",
            "properties": {
                "label:cs": "Kříž se sousoším v Zábřehu na Dvorské ulici",
                "P31": "Pamětní kříž",
                "P31^label:cs": "Pamětní kříž",
                "P131^label:cs": "Zábřeh",
                "P6736": "14672"
            },
            "geometry": {
                "type": "Point",
                "coordinates": [
                    16.87599,
                    49.88636
                ]
            }
        }
    ]
}