{"type":"FeatureCollection","features":[{"type":"Feature","properties":{"label:cs":"Kříž v Lanžhotě u silnice směr Břeclav","P31":"http://www.wikidata.org/entity/Q2309609","P31^label:cs":"Pamětní kříž","P131^label:cs":"Lanžhot","P6736":"27477"},"geometry":{"type":"Point","coordinates":[16.95698,48.73357]}},{"type":"Feature","properties":{"label:cs":"Pamětní deska v Lanžhotě na budově vlakové stanice","P31":"http://www.wikidata.org/entity/Q721747","P31^label:cs":"Pamětní deska","P131^label:cs":"Lanžhot","P6736":"27476"},"geometry":{"type":"Point","coordinates":[16.96226,48.73281]}},{"type":"Feature","properties":{"label:cs":"Boží muka v Lanžhotě na ulici Ivana Olbrachta","P31":"http://www.wikidata.org/entity/Q3395121","P31^label:cs":"Boží muka","P131^label:cs":"Lanžhot","P6736":"27466"},"geometry":{"type":"Point","coordinates":[16.95815,48.72594]}},{"type":"Feature","properties":{"label:cs":"Kříž v Lanžhotě u polní cesty","P31":"http://www.wikidata.org/entity/Q2309609","P31^label:cs":"Pamětní kříž","P131^label:cs":"Lanžhot","P6736":"27465"},"geometry":{"type":"Point","coordinates":[16.95674,48.72736]}},{"type":"Feature","properties":{"label:cs":"Socha svatého Jana Nepomuckého v Lanžhotě u polní cesty","P31":"http://www.wikidata.org/entity/Q179700","P31^label:cs":"Socha","P131^label:cs":"Lanžhot","P6736":"27464"},"geometry":{"type":"Point","coordinates":[16.95048,48.72978]}},{"type":"Feature","properties":{"label:cs":"Kříž v Lanžhotě na okraji obce u vysílače","P31":"http://www.wikidata.org/entity/Q2309609","P31^label:cs":"Pamětní kříž","P131^label:cs":"Lanžhot","P6736":"27463"},"geometry":{"type":"Point","coordinates":[16.95181,48.72605]}},{"type":"Feature","properties":{"label:cs":"Kříž v Lanžhotě na Nové ulici","P31":"http://www.wikidata.org/entity/Q2309609","P31^label:cs":"Pamětní kříž","P131^label:cs":"Lanžhot","P6736":"27462"},"geometry":{"type":"Point","coordinates":[16.95795,48.72266]}},{"type":"Feature","properties":{"label:cs":"Kaplička v Lanžhotě na ulici Kout I","P31":"http://www.wikidata.org/entity/Q14552192","P31^label:cs":"Kaplička","P131^label:cs":"Lanžhot","P6736":"27454"},"geometry":{"type":"Point","coordinates":[16.96087,48.72111]}}]}